best_book_store/__init__.py
people_rest_api/__init__.py
people_rest_api/people.py
people_rest_api-0.0.1.dist-info/LICENSE
people_rest_api-0.0.1.dist-info/METADATA
people_rest_api-0.0.1.dist-info/WHEEL
people_rest_api-0.0.1.dist-info/top_level.txt
people_rest_api-0.0.1.dist-info/RECORD
